rtl/baud_generator.v
module baud_generator(
    input clk,
    input reset,
    output reg baud_tick
);

parameter CLKS_PER_BIT = 10;

reg [3:0] count;

always @(posedge clk or posedge reset) begin
    if (reset) begin
        count <= 0;
        baud_tick <= 0;
    end
    else begin
        if (count == CLKS_PER_BIT - 1) begin
            count <= 0;
            baud_tick <= 1;
        end
        else begin
            count <= count + 1;
            baud_tick <= 0;
        end
    end
end

endmodule

tb/tb_baud_generator.v
`timescale 1ns/1ps

module tb_baud_generator;

reg clk;
reg reset;
wire baud_tick;

// Instantiate the Baud Generator
baud_generator uut (
    .clk(clk),
    .reset(reset),
    .baud_tick(baud_tick)
);

// Clock Generation (10 ns period)
initial begin
    clk = 0;
    forever #5 clk = ~clk;
end

// Generate VCD file for GTKWave
initial begin
    $dumpfile("baud_generator.vcd");
    $dumpvars(0, tb_baud_generator);
end

// Test Sequence
initial begin

    $display("Time\tReset\tBaud_Tick");
    $monitor("%0t\t%b\t%b", $time, reset, baud_tick);

    // Apply Reset
    reset = 1;

    #20;
    reset = 0;

    // Run simulation for some time
    #250;

    $finish;

end

endmodule

baud_generator.vcd
$date
	Sat Jul 04 20:05:36 2026
$end
$version
	Icarus Verilog
$end
$timescale
	1ps
$end
$scope module tb_baud_generator $end
$var wire 1 ! baud_tick $end
$var reg 1 " clk $end
$var reg 1 # reset $end
$scope module uut $end
$var wire 1 " clk $end
$var wire 1 # reset $end
$var parameter 32 $ CLKS_PER_BIT $end
$var reg 1 ! baud_tick $end
$var reg 4 % count [3:0] $end
$upscope $end
$upscope $end
$enddefinitions $end
$comment Show the parameter values. $end
$dumpall
b1010 $
$end
#0
$dumpvars
b0 %
1#
0"
0!
$end
#5000
1"
#10000
0"
#15000
1"
#20000
0"
0#
#25000
b1 %
1"
#30000
0"
#35000
b10 %
1"
#40000
0"
#45000
b11 %
1"
#50000
0"
#55000
b100 %
1"
#60000
0"
#65000
b101 %
1"
#70000
0"
#75000
b110 %
1"
#80000
0"
#85000
b111 %
1"
#90000
0"
#95000
b1000 %
1"
#100000
0"
#105000
b1001 %
1"
#110000
0"
#115000
1!
b0 %
1"
#120000
0"
#125000
0!
b1 %
1"
#130000
0"
#135000
b10 %
1"
#140000
0"
#145000
b11 %
1"
#150000
0"
#155000
b100 %
1"
#160000
0"
#165000
b101 %
1"
#170000
0"
#175000
b110 %
1"
#180000
0"
#185000
b111 %
1"
#190000
0"
#195000
b1000 %
1"
#200000
0"
#205000
b1001 %
1"
#210000
0"
#215000
1!
b0 %
1"
#220000
0"
#225000
0!
b1 %
1"
#230000
0"
#235000
b10 %
1"
#240000
0"
#245000
b11 %
1"
#250000
0"
#255000
b100 %
1"
#260000
0"
#265000
b101 %
1"
