rtl/uart_rx.v
module uart_rx(
    input clk,
    input reset,
    input baud_tick,
    input rx,

    output reg [7:0] data_out,
    output reg data_valid,
    output reg parity_error,
    output reg framing_error
);

reg [3:0] bit_index;
reg [7:0] data_reg;
reg [2:0] state;

parameter IDLE   = 3'b000;
parameter START  = 3'b001;
parameter DATA   = 3'b010;
parameter PARITY = 3'b011;
parameter STOP   = 3'b100;

always @(posedge clk or posedge reset) begin
    if (reset) begin
        bit_index <= 0;
        data_reg <= 0;
        data_out <= 0;
        data_valid <= 0;
        parity_error <= 0;
        framing_error <= 0;
        state <= IDLE;
    end
    else begin
        data_valid <= 0;

        case(state)

        IDLE: begin
            parity_error <= 0;
            framing_error <= 0;

            if (rx == 0)
                state <= START;
        end

        START: begin
            if (baud_tick) begin
                bit_index <= 0;
                state <= DATA;
            end
        end

        DATA: begin
            if (baud_tick) begin
                data_reg[bit_index] <= rx;

                if (bit_index == 7)
                    state <= PARITY;
                else
                    bit_index <= bit_index + 1;
            end
        end

        PARITY: begin
            if (baud_tick) begin
                if (rx != ^data_reg)
                    parity_error <= 1;
                else
                    parity_error <= 0;

                state <= STOP;
            end
        end

        STOP: begin
            if (baud_tick) begin
                if (rx != 1'b1) begin
                    framing_error <= 1;
                    data_valid <= 0;
                end
                else if (parity_error == 0) begin
                    data_out <= data_reg;
                    data_valid <= 1;
                end

                state <= IDLE;
            end
        end

        endcase
    end
end

endmodule

rtl/uart_tx.v
module uart_tx(
    input clk,
    input reset,
    input baud_tick,
    input tx_start,
    input [7:0] data_in,

    output reg tx,
    output reg busy
);

reg [3:0] bit_index;
reg [7:0] data_reg;
reg parity_bit;
reg [2:0] state;

parameter IDLE   = 3'b000;
parameter START  = 3'b001;
parameter DATA   = 3'b010;
parameter PARITY = 3'b011;
parameter STOP   = 3'b100;

always @(posedge clk or posedge reset) begin
    if (reset) begin
        tx <= 1'b1;
        busy <= 1'b0;
        bit_index <= 0;
        data_reg <= 0;
        parity_bit <= 0;
        state <= IDLE;
    end
    else begin
        case (state)

        IDLE: begin
            tx <= 1'b1;
            busy <= 1'b0;

            if (tx_start) begin
                data_reg <= data_in;
                parity_bit <= ^data_in;   // even parity
                bit_index <= 0;
                busy <= 1'b1;
                state <= START;
            end
        end

        START: begin
            if (baud_tick) begin
                tx <= 1'b0;
                state <= DATA;
            end
        end

        DATA: begin
            if (baud_tick) begin
                tx <= data_reg[bit_index];

                if (bit_index == 7)
                    state <= PARITY;
                else
                    bit_index <= bit_index + 1;
            end
        end

        PARITY: begin
            if (baud_tick) begin
                tx <= parity_bit;
                state <= STOP;
            end
        end

        STOP: begin
            if (baud_tick) begin
                tx <= 1'b1;
                busy <= 1'b0;
                state <= IDLE;
            end
        end

        endcase
    end
end

endmodule

rtl/baud_generator.v
module baud_generator(
    input clk,
    input reset,
    output reg baud_tick
);

parameter CLKS_PER_BIT = 10;

reg [3:0] count;

always @(posedge clk or posedge reset) begin
    if (reset) begin
        count <= 0;
        baud_tick <= 0;
    end
    else begin
        if (count == CLKS_PER_BIT - 1) begin
            count <= 0;
            baud_tick <= 1;
        end
        else begin
            count <= count + 1;
            baud_tick <= 0;
        end
    end
end

endmodule

rtl/uart_top.v
module uart_top(
    input clk,
    input reset,
    input tx_start,
    input [7:0] data_in,

    output [7:0] data_out,
    output data_valid,
    output parity_error,
    output framing_error
);

wire baud_tick;
wire tx_wire;

baud_generator baud_gen(
    .clk(clk),
    .reset(reset),
    .baud_tick(baud_tick)
);

uart_tx transmitter(
    .clk(clk),
    .reset(reset),
    .baud_tick(baud_tick),
    .tx_start(tx_start),
    .data_in(data_in),
    .tx(tx_wire),
    .busy()
);

uart_rx receiver(
    .clk(clk),
    .reset(reset),
    .baud_tick(baud_tick),
    .rx(tx_wire),
    .data_out(data_out),
    .data_valid(data_valid),
    .parity_error(parity_error),
    .framing_error(framing_error)
);

endmodule

tb/tb_uart_top.v
`timescale 1ns/1ps

module tb_uart_top;

reg clk;
reg reset;
reg tx_start;
reg [7:0] data_in;

wire [7:0] data_out;
wire data_valid;
wire parity_error;
wire framing_error;

// Instantiate UART Top
uart_top uut (
    .clk(clk),
    .reset(reset),
    .tx_start(tx_start),
    .data_in(data_in),
    .data_out(data_out),
    .data_valid(data_valid),
    .parity_error(parity_error),
    .framing_error(framing_error)
);

// Clock Generation
initial begin
    clk = 0;
    forever #5 clk = ~clk;
end

// Generate VCD
initial begin
    $dumpfile("uart_top.vcd");
    $dumpvars(0, tb_uart_top);
end

// Test Sequence
initial begin

    reset = 1;
    tx_start = 0;
    data_in = 8'hA6;

    #20;
    reset = 0;

    #30;
    tx_start = 1;

    #10;
    tx_start = 0;

    // Wait for complete transmission and reception
    #1600;

    $finish;

end

endmodule

uart_top.vcd
$date
	Sun Jul 05 08:10:59 2026
$end
$version
	Icarus Verilog
$end
$timescale
	1ps
$end
$scope module tb_uart_top $end
$var wire 1 ! parity_error $end
$var wire 1 " framing_error $end
$var wire 1 # data_valid $end
$var wire 8 $ data_out [7:0] $end
$var reg 1 % clk $end
$var reg 8 & data_in [7:0] $end
$var reg 1 ' reset $end
$var reg 1 ( tx_start $end
$scope module uut $end
$var wire 1 % clk $end
$var wire 8 ) data_in [7:0] $end
$var wire 1 ' reset $end
$var wire 1 ( tx_start $end
$var wire 1 * tx_wire $end
$var wire 1 ! parity_error $end
$var wire 1 " framing_error $end
$var wire 1 # data_valid $end
$var wire 8 + data_out [7:0] $end
$var wire 1 , baud_tick $end
$scope module baud_gen $end
$var wire 1 % clk $end
$var wire 1 ' reset $end
$var parameter 32 - CLKS_PER_BIT $end
$var reg 1 , baud_tick $end
$var reg 4 . count [3:0] $end
$upscope $end
$scope module receiver $end
$var wire 1 , baud_tick $end
$var wire 1 % clk $end
$var wire 1 ' reset $end
$var wire 1 * rx $end
$var parameter 3 / DATA $end
$var parameter 3 0 IDLE $end
$var parameter 3 1 PARITY $end
$var parameter 3 2 START $end
$var parameter 3 3 STOP $end
$var reg 4 4 bit_index [3:0] $end
$var reg 8 5 data_out [7:0] $end
$var reg 8 6 data_reg [7:0] $end
$var reg 1 # data_valid $end
$var reg 1 " framing_error $end
$var reg 1 ! parity_error $end
$var reg 3 7 state [2:0] $end
$upscope $end
$scope module transmitter $end
$var wire 1 , baud_tick $end
$var wire 1 % clk $end
$var wire 8 8 data_in [7:0] $end
$var wire 1 ' reset $end
$var wire 1 ( tx_start $end
$var parameter 3 9 DATA $end
$var parameter 3 : IDLE $end
$var parameter 3 ; PARITY $end
$var parameter 3 < START $end
$var parameter 3 = STOP $end
$var reg 4 > bit_index [3:0] $end
$var reg 1 ? busy $end
$var reg 8 @ data_reg [7:0] $end
$var reg 1 A parity_bit $end
$var reg 3 B state [2:0] $end
$var reg 1 * tx $end
$upscope $end
$upscope $end
$upscope $end
$enddefinitions $end
$comment Show the parameter values. $end
$dumpall
b100 =
b1 <
b11 ;
b0 :
b10 9
b100 3
b1 2
b11 1
b0 0
b10 /
b1010 -
$end
#0
$dumpvars
b0 B
0A
b0 @
0?
b0 >
b10100110 8
b0 7
b0 6
b0 5
b0 4
b0 .
0,
b0 +
1*
b10100110 )
0(
1'
b10100110 &
0%
b0 $
0#
0"
0!
$end
#5000
1%
#10000
0%
#15000
1%
#20000
0%
0'
#25000
b1 .
1%
#30000
0%
#35000
b10 .
1%
#40000
0%
#45000
b11 .
1%
#50000
0%
1(
#55000
b100 .
b1 B
1?
b10100110 @
1%
#60000
0%
0(
#65000
b101 .
1%
#70000
0%
#75000
b110 .
1%
#80000
0%
#85000
b111 .
1%
#90000
0%
#95000
b1000 .
1%
#100000
0%
#105000
b1001 .
1%
#110000
0%
#115000
1,
b0 .
1%
#120000
0%
#125000
b10 B
0*
0,
b1 .
1%
#130000
0%
#135000
b10 .
b1 7
1%
#140000
0%
#145000
b11 .
1%
#150000
0%
#155000
b100 .
1%
#160000
0%
#165000
b101 .
1%
#170000
0%
#175000
b110 .
1%
#180000
0%
#185000
b111 .
1%
#190000
0%
#195000
b1000 .
1%
#200000
0%
#205000
b1001 .
1%
#210000
0%
#215000
1,
b0 .
1%
#220000
0%
#225000
b10 7
b1 >
0,
b1 .
1%
#230000
0%
#235000
b10 .
1%
#240000
0%
#245000
b11 .
1%
#250000
0%
#255000
b100 .
1%
#260000
0%
#265000
b101 .
1%
#270000
0%
#275000
b110 .
1%
#280000
0%
#285000
b111 .
1%
#290000
0%
#295000
b1000 .
1%
#300000
0%
#305000
b1001 .
1%
#310000
0%
#315000
1,
b0 .
1%
#320000
0%
#325000
b1 4
b10 >
1*
0,
b1 .
1%
#330000
0%
#335000
b10 .
1%
#340000
0%
#345000
b11 .
1%
#350000
0%
#355000
b100 .
1%
#360000
0%
#365000
b101 .
1%
#370000
0%
#375000
b110 .
1%
#380000
0%
#385000
b111 .
1%
#390000
0%
#395000
b1000 .
1%
#400000
0%
#405000
b1001 .
1%
#410000
0%
#415000
1,
b0 .
1%
#420000
0%
#425000
b10 4
b10 6
b11 >
0,
b1 .
1%
#430000
0%
#435000
b10 .
1%
#440000
0%
#445000
b11 .
1%
#450000
0%
#455000
b100 .
1%
#460000
0%
#465000
b101 .
1%
#470000
0%
#475000
b110 .
1%
#480000
0%
#485000
b111 .
1%
#490000
0%
#495000
b1000 .
1%
#500000
0%
#505000
b1001 .
1%
#510000
0%
#515000
1,
b0 .
1%
#520000
0%
#525000
b11 4
b110 6
b100 >
0*
0,
b1 .
1%
#530000
0%
#535000
b10 .
1%
#540000
0%
#545000
b11 .
1%
#550000
0%
#555000
b100 .
1%
#560000
0%
#565000
b101 .
1%
#570000
0%
#575000
b110 .
1%
#580000
0%
#585000
b111 .
1%
#590000
0%
#595000
b1000 .
1%
#600000
0%
#605000
b1001 .
1%
#610000
0%
#615000
1,
b0 .
1%
#620000
0%
#625000
b100 4
b101 >
0,
b1 .
1%
#630000
0%
#635000
b10 .
1%
#640000
0%
#645000
b11 .
1%
#650000
0%
#655000
b100 .
1%
#660000
0%
#665000
b101 .
1%
#670000
0%
#675000
b110 .
1%
#680000
0%
#685000
b111 .
1%
#690000
0%
#695000
b1000 .
1%
#700000
0%
#705000
b1001 .
1%
#710000
0%
#715000
1,
b0 .
1%
#720000
0%
#725000
b101 4
b110 >
1*
0,
b1 .
1%
#730000
0%
#735000
b10 .
1%
#740000
0%
#745000
b11 .
1%
#750000
0%
#755000
b100 .
1%
#760000
0%
#765000
b101 .
1%
#770000
0%
#775000
b110 .
1%
#780000
0%
#785000
b111 .
1%
#790000
0%
#795000
b1000 .
1%
#800000
0%
#805000
b1001 .
1%
#810000
0%
#815000
1,
b0 .
1%
#820000
0%
#825000
b110 4
b100110 6
b111 >
0*
0,
b1 .
1%
#830000
0%
#835000
b10 .
1%
#840000
0%
#845000
b11 .
1%
#850000
0%
#855000
b100 .
1%
#860000
0%
#865000
b101 .
1%
#870000
0%
#875000
b110 .
1%
#880000
0%
#885000
b111 .
1%
#890000
0%
#895000
b1000 .
1%
#900000
0%
#905000
b1001 .
1%
#910000
0%
#915000
1,
b0 .
1%
#920000
0%
#925000
b111 4
b11 B
1*
0,
b1 .
1%
#930000
0%
#935000
b10 .
1%
#940000
0%
#945000
b11 .
1%
#950000
0%
#955000
b100 .
1%
#960000
0%
#965000
b101 .
1%
#970000
0%
#975000
b110 .
1%
#980000
0%
#985000
b111 .
1%
#990000
0%
#995000
b1000 .
1%
#1000000
0%
#1005000
b1001 .
1%
#1010000
0%
#1015000
1,
b0 .
1%
#1020000
0%
#1025000
b11 7
b10100110 6
b100 B
0*
0,
b1 .
1%
#1030000
0%
#1035000
b10 .
1%
#1040000
0%
#1045000
b11 .
1%
#1050000
0%
#1055000
b100 .
1%
#1060000
0%
#1065000
b101 .
1%
#1070000
0%
#1075000
b110 .
1%
#1080000
0%
#1085000
b111 .
1%
#1090000
0%
#1095000
b1000 .
1%
#1100000
0%
#1105000
b1001 .
1%
#1110000
0%
#1115000
1,
b0 .
1%
#1120000
0%
#1125000
b100 7
b0 B
0?
1*
0,
b1 .
1%
#1130000
0%
#1135000
b10 .
1%
#1140000
0%
#1145000
b11 .
1%
#1150000
0%
#1155000
b100 .
1%
#1160000
0%
#1165000
b101 .
1%
#1170000
0%
#1175000
b110 .
1%
#1180000
0%
#1185000
b111 .
1%
#1190000
0%
#1195000
b1000 .
1%
#1200000
0%
#1205000
b1001 .
1%
#1210000
0%
#1215000
1,
b0 .
1%
#1220000
0%
#1225000
b0 7
1#
b10100110 $
b10100110 +
b10100110 5
0,
b1 .
1%
#1230000
0%
#1235000
b10 .
0#
1%
#1240000
0%
#1245000
b11 .
1%
#1250000
0%
#1255000
b100 .
1%
#1260000
0%
#1265000
b101 .
1%
#1270000
0%
#1275000
b110 .
1%
#1280000
0%
#1285000
b111 .
1%
#1290000
0%
#1295000
b1000 .
1%
#1300000
0%
#1305000
b1001 .
1%
#1310000
0%
#1315000
1,
b0 .
1%
#1320000
0%
#1325000
0,
b1 .
1%
#1330000
0%
#1335000
b10 .
1%
#1340000
0%
#1345000
b11 .
1%
#1350000
0%
#1355000
b100 .
1%
#1360000
0%
#1365000
b101 .
1%
#1370000
0%
#1375000
b110 .
1%
#1380000
0%
#1385000
b111 .
1%
#1390000
0%
#1395000
b1000 .
1%
#1400000
0%
#1405000
b1001 .
1%
#1410000
0%
#1415000
1,
b0 .
1%
#1420000
0%
#1425000
0,
b1 .
1%
#1430000
0%
#1435000
b10 .
1%
#1440000
0%
#1445000
b11 .
1%
#1450000
0%
#1455000
b100 .
1%
#1460000
0%
#1465000
b101 .
1%
#1470000
0%
#1475000
b110 .
1%
#1480000
0%
#1485000
b111 .
1%
#1490000
0%
#1495000
b1000 .
1%
#1500000
0%
#1505000
b1001 .
1%
#1510000
0%
#1515000
1,
b0 .
1%
#1520000
0%
#1525000
0,
b1 .
1%
#1530000
0%
#1535000
b10 .
1%
#1540000
0%
#1545000
b11 .
1%
#1550000
0%
#1555000
b100 .
1%
#1560000
0%
#1565000
b101 .
1%
#1570000
0%
#1575000
b110 .
1%
#1580000
0%
#1585000
b111 .
1%
#1590000
0%
#1595000
b1000 .
1%
#1600000
0%
#1605000
b1001 .
1%
#1610000
0%
#1615000
1,
b0 .
1%
#1620000
0%
#1625000
0,
b1 .
1%
#1630000
0%
#1635000
b10 .
1%
#1640000
0%
#1645000
b11 .
1%
#1650000
0%
#1655000
b100 .
1%
