rtl/uart_tx.v
module uart_tx(
    input clk,
    input reset,
    input baud_tick,
    input tx_start,
    input [7:0] data_in,

    output reg tx,
    output reg busy
);

reg [3:0] bit_index;
reg [7:0] data_reg;
reg parity_bit;
reg [2:0] state;

parameter IDLE   = 3'b000;
parameter START  = 3'b001;
parameter DATA   = 3'b010;
parameter PARITY = 3'b011;
parameter STOP   = 3'b100;

always @(posedge clk or posedge reset) begin
    if (reset) begin
        tx <= 1'b1;
        busy <= 1'b0;
        bit_index <= 0;
        data_reg <= 0;
        parity_bit <= 0;
        state <= IDLE;
    end
    else begin
        case (state)

        IDLE: begin
            tx <= 1'b1;
            busy <= 1'b0;

            if (tx_start) begin
                data_reg <= data_in;
                parity_bit <= ^data_in;   // even parity
                bit_index <= 0;
                busy <= 1'b1;
                state <= START;
            end
        end

        START: begin
            if (baud_tick) begin
                tx <= 1'b0;
                state <= DATA;
            end
        end

        DATA: begin
            if (baud_tick) begin
                tx <= data_reg[bit_index];

                if (bit_index == 7)
                    state <= PARITY;
                else
                    bit_index <= bit_index + 1;
            end
        end

        PARITY: begin
            if (baud_tick) begin
                tx <= parity_bit;
                state <= STOP;
            end
        end

        STOP: begin
            if (baud_tick) begin
                tx <= 1'b1;
                busy <= 1'b0;
                state <= IDLE;
            end
        end

        endcase
    end
end

endmodule

tb/tb_uart_tx.v
`timescale 1ns/1ps

module tb_uart_tx;

reg clk;
reg reset;
reg baud_tick;
reg tx_start;
reg [7:0] data_in;

wire tx;
wire busy;

// Instantiate UART Transmitter
uart_tx uut (
    .clk(clk),
    .reset(reset),
    .baud_tick(baud_tick),
    .tx_start(tx_start),
    .data_in(data_in),
    .tx(tx),
    .busy(busy)
);

// Clock Generation (10 ns period)
initial begin
    clk = 0;
    forever #5 clk = ~clk;
end

// Baud Tick Generation (every 50 ns)
initial begin
    baud_tick = 0;
    forever begin
        #45 baud_tick = 1;
        #10 baud_tick = 0;
    end
end

// VCD Dump
initial begin
    $dumpfile("uart_tx.vcd");
    $dumpvars(0, tb_uart_tx);
end

// Test Sequence
initial begin

    reset = 1;
    tx_start = 0;
    data_in = 8'hA6;

    #20;
    reset = 0;

    #20;
    tx_start = 1;

    #10;
    tx_start = 0;

    #700;

    $finish;

end

endmodule

uart_tx.vcd
$date
	Sun Jul 05 07:56:39 2026
$end
$version
	Icarus Verilog
$end
$timescale
	1ps
$end
$scope module tb_uart_tx $end
$var wire 1 ! tx $end
$var wire 1 " busy $end
$var reg 1 # baud_tick $end
$var reg 1 $ clk $end
$var reg 8 % data_in [7:0] $end
$var reg 1 & reset $end
$var reg 1 ' tx_start $end
$scope module uut $end
$var wire 1 # baud_tick $end
$var wire 1 $ clk $end
$var wire 8 ( data_in [7:0] $end
$var wire 1 & reset $end
$var wire 1 ' tx_start $end
$var parameter 3 ) DATA $end
$var parameter 3 * IDLE $end
$var parameter 3 + PARITY $end
$var parameter 3 , START $end
$var parameter 3 - STOP $end
$var reg 4 . bit_index [3:0] $end
$var reg 1 " busy $end
$var reg 8 / data_reg [7:0] $end
$var reg 1 0 parity_bit $end
$var reg 3 1 state [2:0] $end
$var reg 1 ! tx $end
$upscope $end
$upscope $end
$enddefinitions $end
$comment Show the parameter values. $end
$dumpall
b100 -
b1 ,
b11 +
b0 *
b10 )
$end
#0
$dumpvars
b0 1
00
b0 /
b0 .
b10100110 (
0'
1&
b10100110 %
0$
0#
0"
1!
$end
#5000
1$
#10000
0$
#15000
1$
#20000
0$
0&
#25000
1$
#30000
0$
#35000
1$
#40000
0$
1'
#45000
b1 1
1"
b10100110 /
1$
1#
#50000
0$
0'
#55000
1$
0#
#60000
0$
#65000
1$
#70000
0$
#75000
1$
#80000
0$
#85000
1$
#90000
0$
#95000
1$
#100000
0$
1#
#105000
b10 1
0!
1$
#110000
0$
0#
#115000
1$
#120000
0$
#125000
1$
#130000
0$
#135000
1$
#140000
0$
#145000
1$
#150000
0$
#155000
b1 .
1$
1#
#160000
0$
#165000
1$
0#
#170000
0$
#175000
1$
#180000
0$
#185000
1$
#190000
0$
#195000
1$
#200000
0$
#205000
1$
#210000
0$
1#
#215000
b10 .
1!
1$
#220000
0$
0#
#225000
1$
#230000
0$
#235000
1$
#240000
0$
#245000
1$
#250000
0$
#255000
1$
#260000
0$
#265000
b11 .
1$
1#
#270000
0$
#275000
1$
0#
#280000
0$
#285000
1$
#290000
0$
#295000
1$
#300000
0$
#305000
1$
#310000
0$
#315000
1$
#320000
0$
1#
#325000
b100 .
0!
1$
#330000
0$
0#
#335000
1$
#340000
0$
#345000
1$
#350000
0$
#355000
1$
#360000
0$
#365000
1$
#370000
0$
#375000
b101 .
1$
1#
#380000
0$
#385000
1$
0#
#390000
0$
#395000
1$
#400000
0$
#405000
1$
#410000
0$
#415000
1$
#420000
0$
#425000
1$
#430000
0$
1#
#435000
b110 .
1!
1$
#440000
0$
0#
#445000
1$
#450000
0$
#455000
1$
#460000
0$
#465000
1$
#470000
0$
#475000
1$
#480000
0$
#485000
b111 .
0!
1$
1#
#490000
0$
#495000
1$
0#
#500000
0$
#505000
1$
#510000
0$
#515000
1$
#520000
0$
#525000
1$
#530000
0$
#535000
1$
#540000
0$
1#
#545000
b11 1
1!
1$
#550000
0$
0#
#555000
1$
#560000
0$
#565000
1$
#570000
0$
#575000
1$
#580000
0$
#585000
1$
#590000
0$
#595000
b100 1
0!
1$
1#
#600000
0$
#605000
1$
0#
#610000
0$
#615000
1$
#620000
0$
#625000
1$
#630000
0$
#635000
1$
#640000
0$
#645000
1$
#650000
0$
1#
#655000
b0 1
0"
1!
1$
#660000
0$
0#
#665000
1$
#670000
0$
#675000
1$
#680000
0$
#685000
1$
#690000
0$
#695000
1$
#700000
0$
#705000
1$
1#
#710000
0$
#715000
1$
0#
